LICENSE
README.md
nautobot_secrets_providers/__init__.py
nautobot_secrets_providers/migrations/__init__.py
nautobot_secrets_providers/providers/__init__.py
nautobot_secrets_providers/providers/aws.py
nautobot_secrets_providers/providers/azure.py
nautobot_secrets_providers/providers/choices.py
nautobot_secrets_providers/providers/delinea.py
nautobot_secrets_providers/providers/hashicorp.py
nautobot_secrets_providers/secrets.py
nautobot_secrets_providers/templates/nautobot_secrets_providers/home.html
nautobot_secrets_providers/tests/__init__.py
nautobot_secrets_providers/tests/nautobot_config.py
nautobot_secrets_providers/tests/test_basic.py
nautobot_secrets_providers/tests/test_providers.py
nautobot_secrets_providers/urls.py
nautobot_secrets_providers/views.py
nautobot_secrets_providers_l8_azure-0.1.0.dist-info/LICENSE
nautobot_secrets_providers_l8_azure-0.1.0.dist-info/METADATA
nautobot_secrets_providers_l8_azure-0.1.0.dist-info/WHEEL
nautobot_secrets_providers_l8_azure-0.1.0.dist-info/RECORD
