Metadata-Version: 2.1
Name: nautobot-secrets-providers-l8-azure
Version: 0.1.0
Summary: Nautobot Secrets Providers App
Home-page: https://github.com/nautobot/nautobot-app-secrets-providers
License: Apache-2.0
Keywords: nautobot,nautobot-plugin,nautobot-app
Author: Network to Code, LLC
Author-email: opensource@networktocode.com
Requires-Python: >=3.8,<3.12
Classifier: Development Status :: 5 - Production/Stable
Classifier: Intended Audience :: Developers
Classifier: License :: OSI Approved :: Apache Software License
Classifier: Programming Language :: Python :: 3
Classifier: Programming Language :: Python :: 3.8
Classifier: Programming Language :: Python :: 3.9
Classifier: Programming Language :: Python :: 3.10
Classifier: Programming Language :: Python :: 3.11
Provides-Extra: all
Provides-Extra: aws
Provides-Extra: azure
Provides-Extra: hashicorp
Provides-Extra: nautobot
Provides-Extra: thycotic
Requires-Dist: azure-identity (>=1.15.0,<2.0.0) ; extra == "all" or extra == "azure"
Requires-Dist: azure-keyvault-secrets (>=4.8.0,<5.0.0) ; extra == "all" or extra == "azure"
Requires-Dist: boto3 (>=1.19.5,<1.20.0) ; extra == "all" or extra == "aws"
Requires-Dist: hvac (>=0.11.0,<1.1.0) ; extra == "all" or extra == "hashicorp"
Requires-Dist: nautobot (>=2.0.0,<3.0.0) ; extra == "nautobot"
Requires-Dist: python-tss-sdk (>=1.2.0,<1.3.0) ; extra == "all" or extra == "thycotic"
Project-URL: Repository, https://github.com/nautobot/nautobot-app-secrets-providers
